sphinx_gmt/__init__.py
sphinx_gmt/gmtplot.py
sphinx_gmt-0.3.0.dist-info/AUTHORS.md
sphinx_gmt-0.3.0.dist-info/LICENSE.txt
sphinx_gmt-0.3.0.dist-info/METADATA
sphinx_gmt-0.3.0.dist-info/WHEEL
sphinx_gmt-0.3.0.dist-info/top_level.txt
sphinx_gmt-0.3.0.dist-info/RECORD
