Metadata-Version: 2.1
Name: sphinx-gmt
Version: 0.3.0
Summary: Sphinx extensions for the Generic Mapping Tools
Home-page: https://github.com/GenericMappingTools/sphinx_gmt
Author: The GMT Developers
Author-email: 
Maintainer: The GMT Developers
Maintainer-email: 
License: BSD License
Platform: Any
Classifier: Development Status :: 3 - Alpha
Classifier: Intended Audience :: Science/Research
Classifier: Intended Audience :: Developers
Classifier: Intended Audience :: Education
Classifier: Topic :: Scientific/Engineering
Classifier: Topic :: Software Development :: Libraries
Classifier: Programming Language :: Python :: 3.8
Classifier: Programming Language :: Python :: 3.9
Classifier: Programming Language :: Python :: 3.10
Classifier: License :: OSI Approved :: BSD License
Requires-Python: >=3.8
License-File: LICENSE.txt
License-File: AUTHORS.md
Requires-Dist: jinja2
Requires-Dist: sphinx
